tests/__init__.py
tests/test_EN_US.py
words2num/__init__.py
words2num/base.py
words2num/core.py
words2num/lang_EN_US.py
words2num-0.2.2.dist-info/METADATA
words2num-0.2.2.dist-info/RECORD
words2num-0.2.2.dist-info/WHEEL
words2num-0.2.2.dist-info/top_level.txt
