Metadata-Version: 2.1
Name: words2num
Version: 0.2.2
Summary: Inverse text normalization for numbers
Home-page: http://github.com/JDongian/python-words2num
Author: Joshua Dong
Author-email: jdong42@gmail.com
License: UNKNOWN
Platform: UNKNOWN
